Metadata-Version: 2.1
Name: odoo12-addon-cooperator-subscription-form-without-share-number
Version: 12.0.1.0.0
Summary: Remove field share number from cooperator subscription form.
Home-page: https://coopdevs.org
Author: Coopdevs Treball SCCL
License: AGPL-3
Platform: UNKNOWN
Classifier: Programming Language :: Python
Classifier: Framework :: Odoo
Classifier: Framework :: Odoo :: 12.0
Classifier: License :: OSI Approved :: GNU Affero General Public License v3
Requires-Python: >=3.5
Requires-Dist: odoo12-addon-easy-my-coop-website
Requires-Dist: odoo (<12.1dev,>=12.0a)
